pokesim/__init__.py
pokesim/color.py
pokesim/constants.py
pokesim/move.py
pokesim/nature.py
pokesim/parse.py
pokesim/pokemon.py
pokesim/poketypes.py
pokesim/utils.py
pokesim/data/moves/Amnesia
pokesim/data/moves/Double Team
pokesim/data/moves/Growl
pokesim/data/moves/Razor Leaf
pokesim/data/moves/Seed Bomb
pokesim/data/moves/Sweet Scent
pokesim/data/moves/Swords Dance
pokesim/data/moves/Tackle
pokesim/data/moves/Vine Whip
pokesim/data/moves/Work Up
pokesim/data/pokemon/Bulbasaur
pokesim-0.2.0.dist-info/LICENSE.txt
pokesim-0.2.0.dist-info/METADATA
pokesim-0.2.0.dist-info/WHEEL
pokesim-0.2.0.dist-info/entry_points.txt
pokesim-0.2.0.dist-info/top_level.txt
pokesim-0.2.0.dist-info/RECORD
