Metadata-Version: 2.1
Name: pokesim
Version: 0.2.0
Summary: Simulates a pokemon battle with a computer opponent
Home-page: https://github.com/ocket8888/pokesim/tree/master/python
Author: ocket8888
Author-email: ocket8888@gmail.com
License: UNKNOWN
Keywords: pokemon simulation game battle
Platform: UNKNOWN
Classifier: Development Status :: 3 - Alpha
Classifier: Environment :: Console
Classifier: Natural Language :: English
Classifier: Intended Audience :: End Users/Desktop
Classifier: Topic :: Games/Entertainment :: Role-Playing
Classifier: Topic :: Games/Entertainment :: Simulation
Classifier: License :: Public Domain
Classifier: Programming Language :: Python :: 3.6
Classifier: Programming Language :: Python :: 3.7
Requires-Python: ~=3.10
License-File: LICENSE.txt
Requires-Dist: readline
Requires-Dist: setuptools
Requires-Dist: typing
